create_remote_repo_and_push/__init__.py
create_remote_repo_and_push/create_remote_repo_and_push.py
create_remote_repo_and_push/enum/Command.py
create_remote_repo_and_push/enum/GitHub_API.py
create_remote_repo_and_push/enum/__init__.py
create_remote_repo_and_push/handlers/BaseHandler.py
create_remote_repo_and_push/handlers/CreateGitignoreHandler.py
create_remote_repo_and_push/handlers/CreateRemoteRepoHandler.py
create_remote_repo_and_push/handlers/__init__.py
create_remote_repo_and_push/helpers/__init__.py
create_remote_repo_and_push/helpers/run_command.py
create_remote_repo_and_push/models/Repository.py
create_remote_repo_and_push/models/__init__.py
create_remote_repo-1.0.0.dist-info/LICENSE
create_remote_repo-1.0.0.dist-info/METADATA
create_remote_repo-1.0.0.dist-info/WHEEL
create_remote_repo-1.0.0.dist-info/entry_points.txt
create_remote_repo-1.0.0.dist-info/top_level.txt
create_remote_repo-1.0.0.dist-info/RECORD
