Metadata-Version: 2.1
Name: create-remote-repo
Version: 1.0.0
Summary: This command line tool automates the process of initializing a local Git repository, creating a remote GitHub repository via the GitHub API, optionally adding a .gitignore file, staging changes, committing, and performing the initial push to the remote repository.
Home-page: 
Author: Kim Chung
Author-email: Kim Chung <kchung0802@gmail.com>
License: MIT License
Project-URL: Repository, https://github.com/Kimmm-c/automate-create-remote-repo
Keywords: github,automation,create,remote repository
Classifier: Programming Language :: Python :: 3
Classifier: License :: OSI Approved :: MIT License
Classifier: Operating System :: MacOS
Requires-Python: >=3.7
License-File: LICENSE
Requires-Dist: requests (~=2.31.0)
